{
	"settings": {
		"appearanceTools": true,
		"color": {
			"palette": [
				{
					"color": "#16161d",
					"name": "Base",
					"slug": "base"
				},
				{
					"color": "#ffffff",
					"name": "Contrast",
					"slug": "contrast"
				},
				{
					"color": "#ff0000",
					"name": "Primary",
					"slug": "primary"
				},
				{
					"color": "#00ff00",
					"name": "Secondary",
					"slug": "secondary"
				},
				{
					"color": "#0000ff",
					"name": "Tertiary",
					"slug": "tertiary"
				}
			]
		},
		"typography": {
			"fontFamilies": [
				{
					"fontFace": [
						{
							"fontFamily": "Roboto",
							"fontStyle": "normal",
							"fontWeight": "400",
							"src": [
								"file:./assets/fonts/roboto_normal_400.ttf"
							]
						},
						{
							"fontFamily": "Roboto",
							"fontStyle": "italic",
							"fontWeight": "400",
							"src": [
								"file:./assets/fonts/roboto_italic_400.ttf"
							]
						},
						{
							"fontFamily": "Roboto",
							"fontStyle": "normal",
							"fontWeight": "700",
							"src": [
								"file:./assets/fonts/roboto_normal_700.ttf"
							]
						},
						{
							"fontFamily": "Roboto",
							"fontStyle": "italic",
							"fontWeight": "700",
							"src": [
								"file:./assets/fonts/roboto_italic_700.ttf"
							]
						}
					],
					"fontFamily": "Roboto",
					"slug": "roboto"
				}
			]
		}
	},
	"styles": {
		"blocks": {
			"core/navigation": {
				"spacing": {
					"blockGap": "0px"
				}
			}
		},
		"color": {
			"background": "var:preset|color|base",
			"text": "var:preset|color|contrast"
		},
		"elements": {
			"button": {
				"color": {
					"background": "var:preset|color|primary",
					"text": "var:preset|color|contrast"
				},
				"typography": {
					"fontFamily": "var:preset|font-family|roboto"
				}
			},
			"heading": {
				"color": {
					"background": "var:preset|color|tertiary",
					"text": "#ffffff"
				},
				"typography": {
					"fontFamily": "var:preset|font-family|roboto"
				}
			},
			"link": {
				":hover": {
					"color": {
						"text": "var:preset|color|tertiary"
					}
				},
				"color": {
					"text": "var:preset|color|secondary"
				},
				"typography": {
					"fontFamily": "var:preset|font-family|roboto"
				}
			}
		},
		"spacing": {
			"blockGap": "0px",
			"padding": {
				"bottom": "0px",
				"left": "0px",
				"right": "0px",
				"top": "0px"
			}
		},
		"typography": {
			"fontFamily": "var:preset|font-family|roboto"
		}
	},
	"version": 2,
	"$schema": "https://schemas.wp.org/wp/6.2/theme.json"
}